setup.cfg
setup.py
libgql/__init__.py
libgql/test_simple_queries.py
libgql.egg-info/PKG-INFO
libgql.egg-info/SOURCES.txt
libgql.egg-info/dependency_links.txt
libgql.egg-info/requires.txt
libgql.egg-info/top_level.txt
libgql/snapshots/__init__.py
libgql/snapshots/snap_test_simple_queries.py