Metadata-Version: 1.1
Name: libgql
Version: 0.0.1
Summary: GraphQL Linked Library bindings for python
Home-page: https://github.com/brysgo/libgql
Author: Bryan Goldstein
Author-email: brysgo@gmail.com
License: MIT
Keywords: graphql languagebindings development
Platform: UNKNOWN
Classifier: Development Status :: 3 - Alpha
Classifier: Intended Audience :: Developers
Classifier: Topic :: Software Development :: Libraries
Classifier: License :: OSI Approved :: MIT License
Classifier: Programming Language :: Python :: 3
Classifier: Programming Language :: Python :: 3.3
Classifier: Programming Language :: Python :: 3.4
Classifier: Programming Language :: Python :: 3.5
